antiai/__init__.py
antiai/__version__.py
antiai/core/__init__.py
antiai/core/decoder.py
antiai/core/encoder.py
antiai/core/exceptions.py
antiai/core/format_spec.py
antiai/detection/__init__.py
antiai/detection/perceptual_hash.py
antiai/detection/tampering.py
antiai/protection/__init__.py
antiai/protection/adversarial.py
antiai/protection/metadata.py
antiai/protection/watermark.py
antiai/utils/__init__.py
antiai/utils/image_ops.py
antiai/utils/logger.py
antiai/validation/verify.py
antiai-0.1.0.dist-info/licenses/LICENSE
antiai-0.1.0.dist-info/METADATA
antiai-0.1.0.dist-info/WHEEL
antiai-0.1.0.dist-info/entry_points.txt
antiai-0.1.0.dist-info/top_level.txt
antiai-0.1.0.dist-info/RECORD
