Metadata-Version: 2.4
Name: antiai
Version: 0.1.0
Summary: Advanced image protection system against AI training and unauthorized use
Author-email: Miguel <miguel@alamopscloud.com>
Maintainer-email: Miguel <miguel@alamopscloud.com>
License: MIT
Project-URL: Homepage, https://github.com/miguel/antiai
Project-URL: Documentation, https://antiai.readthedocs.io
Project-URL: Repository, https://github.com/miguel/antiai
Project-URL: Bug Tracker, https://github.com/miguel/antiai/issues
Keywords: image-protection,adversarial,watermarking,ai-protection,digital-rights,computer-vision
Classifier: Development Status :: 4 - Beta
Classifier: Intended Audience :: Developers
Classifier: Intended Audience :: Science/Research
Classifier: License :: OSI Approved :: MIT License
Classifier: Operating System :: OS Independent
Classifier: Programming Language :: Python :: 3
Classifier: Programming Language :: Python :: 3.9
Classifier: Programming Language :: Python :: 3.10
Classifier: Programming Language :: Python :: 3.11
Classifier: Programming Language :: Python :: 3.12
Classifier: Topic :: Multimedia :: Graphics
Classifier: Topic :: Scientific/Engineering :: Artificial Intelligence
Classifier: Topic :: Security
Classifier: Typing :: Typed
Requires-Python: >=3.9
License-File: LICENSE
Requires-Dist: numpy>=1.24.0
Requires-Dist: pillow>=10.0.0
Requires-Dist: torch>=2.0.0
Requires-Dist: torchvision>=0.15.0
Requires-Dist: pywavelets>=1.4.1
Requires-Dist: scipy>=1.11.0
Requires-Dist: cryptography>=41.0.0
Requires-Dist: pydantic>=2.0.0
Requires-Dist: typing-extensions>=4.8.0
Provides-Extra: dev
Requires-Dist: pytest>=7.4.0; extra == "dev"
Requires-Dist: pytest-cov>=4.1.0; extra == "dev"
Requires-Dist: pytest-asyncio>=0.21.0; extra == "dev"
Requires-Dist: black>=23.7.0; extra == "dev"
Requires-Dist: ruff>=0.0.285; extra == "dev"
Requires-Dist: mypy>=1.5.0; extra == "dev"
Requires-Dist: pre-commit>=3.3.3; extra == "dev"
Requires-Dist: isort>=5.12.0; extra == "dev"
Provides-Extra: docs
Requires-Dist: mkdocs>=1.5.0; extra == "docs"
Requires-Dist: mkdocs-material>=9.2.0; extra == "docs"
Requires-Dist: mkdocstrings[python]>=0.22.0; extra == "docs"
Provides-Extra: benchmark
Requires-Dist: pytest-benchmark>=4.0.0; extra == "benchmark"
Requires-Dist: memory-profiler>=0.61.0; extra == "benchmark"
Dynamic: license-file
